{
  "ACL1559": "226", 
  "ACL7650": "232", 
  "ACL9506": "393", 
  "ACL9681": "219", 
  "AT&SF0470": "281", 
  "AT&SF1316": "401", 
  "AT&SF1641": "390", 
  "AT&SF2505": "308", 
  "AT&SF5719": "480", 
  "AT&SF6107": "477", 
  "AT&SF7468": "478", 
  "AT&SF9123": "476", 
  "AT&SF9353": "306", 
  "AT&SF9839": "426", 
  "B&A4834": "421", 
  "B&A6122": "221", 
  "B&A7184": "331", 
  "B&O0424": "137", 
  "B&O0625": "457", 
  "B&O1965": "459", 
  "B&O2120": "483", 
  "B&O2165": "462", 
  "B&O2221": "448", 
  "B&O2342": "178", 
  "B&O2662": "150", 
  "B&O3915": "467", 
  "B&O4164": "79", 
  "B&O4231": "447", 
  "B&O4529": "177", 
  "B&O5848": "50", 
  "B&O6136": "268", 
  "B&O6166": "152", 
  "B&O6272": "216", 
  "B&O6284": "172", 
  "B&O7328": "129", 
  "B&O7422": "183", 
  "B&O7971": "78", 
  "B&O8109": "215", 
  "B&O8993": "182", 
  "B&O9120": "409", 
  "B&O9246": "269", 
  "B&O9279": "128", 
  "B&O9347": "442", 
  "B&O9372": "166", 
  "B&O9632": "155", 
  "B&O9682": "180", 
  "CNJ2387": "491", 
  "CNJ4251": "420", 
  "CNJ5875": "307", 
  "CNJ6249": "30", 
  "CNJ9144": "425", 
  "DL&W0802": "391", 
  "DL&W1178": "239", 
  "DL&W1879": "472", 
  "DL&W2271": "484", 
  "DL&W2438": "399", 
  "DL&W3830": "339", 
  "DL&W4653": "23", 
  "DL&W4869": "346", 
  "DL&W6167": "280", 
  "DL&W6357": "279", 
  "DL&W6882": "35", 
  "DL&W8383": "435", 
  "DL&W9108": "474", 
  "DL&W9551": "424", 
  "DL&W9971": "233", 
  "ER1259": "469", 
  "ER1487": "410", 
  "ER1635": "479", 
  "ER2236": "398", 
  "ER2641": "481", 
  "ER4445": "45", 
  "ER5044": "384", 
  "ER5590": "395", 
  "ER6944": "422", 
  "ET125": "125", 
  "ET127": "127", 
  "ET190": "190", 
  "ET192": "192", 
  "ET2": "2", 
  "ET212": "212", 
  "ET247": "247", 
  "ET249": "249", 
  "ET251": "251", 
  "ET253": "253", 
  "ET255": "255", 
  "ET257": "257", 
  "ET259": "259", 
  "ET261": "261", 
  "ET263": "263", 
  "ET294": "294", 
  "ET383": "383", 
  "ET495": "495", 
  "ET83": "83", 
  "ET85": "85", 
  "FGEX0318": "503", 
  "FGEX0377": "522", 
  "FGEX0396": "365", 
  "FGEX0434": "499", 
  "FGEX0572": "363", 
  "FGEX0756": "14", 
  "FGEX0860": "367", 
  "FGEX1013": "15", 
  "FGEX1407": "507", 
  "FGEX1411": "513", 
  "FGEX1443": "496", 
  "FGEX1456": "523", 
  "FGEX1583": "369", 
  "FGEX1666": "317", 
  "FGEX1876": "316", 
  "FGEX2315": "321", 
  "FGEX2408": "315", 
  "FGEX2786": "314", 
  "FGEX2997": "372", 
  "FGEX3021": "520", 
  "FGEX3041": "512", 
  "FGEX3336": "312", 
  "FGEX3534": "366", 
  "FGEX3627": "519", 
  "FGEX3726": "528", 
  "FGEX4001": "506", 
  "FGEX4050": "510", 
  "FGEX4272": "511", 
  "FGEX4436": "11", 
  "FGEX4602": "531", 
  "FGEX4661": "530", 
  "FGEX4698": "9", 
  "FGEX4947": "320", 
  "FGEX4968": "526", 
  "FGEX5119": "364", 
  "FGEX5180": "318", 
  "FGEX5183": "505", 
  "FGEX5189": "517", 
  "FGEX5228": "370", 
  "FGEX5718": "501", 
  "FGEX5795": "313", 
  "FGEX5882": "529", 
  "FGEX6020": "509", 
  "FGEX6124": "362", 
  "FGEX6451": "521", 
  "FGEX6561": "516", 
  "FGEX6654": "368", 
  "FGEX6930": "498", 
  "FGEX7192": "515", 
  "FGEX7384": "322", 
  "FGEX7438": "18", 
  "FGEX7585": "504", 
  "FGEX7800": "500", 
  "FGEX7939": "16", 
  "FGEX7961": "514", 
  "FGEX8007": "8", 
  "FGEX8162": "525", 
  "FGEX8213": "518", 
  "FGEX8326": "324", 
  "FGEX8382": "502", 
  "FGEX8422": "13", 
  "FGEX8655": "12", 
  "FGEX8707": "508", 
  "FGEX8803": "524", 
  "FGEX8821": "497", 
  "FGEX8916": "7", 
  "FGEX9183": "527", 
  "FGEX9219": "17", 
  "FGEX9714": "319", 
  "FGEX9864": "361", 
  "FGEX9944": "371", 
  "LV2144": "482", 
  "LV2703": "429", 
  "LV4422": "44", 
  "LV4773": "235", 
  "LV5316": "405", 
  "LV5704": "411", 
  "LV7445": "283", 
  "LV8370": "347", 
  "M&P3374": "427", 
  "M&P5095": "222", 
  "M&P6627": "417", 
  "M&P8764": "450", 
  "M&P9456": "345", 
  "NYC1483": "271", 
  "NYC2316": "341", 
  "NYC4456": "43", 
  "NYC5927": "414", 
  "NYC6683": "41", 
  "NYC7386": "412", 
  "NYC8765": "471", 
  "NYC9791": "485", 
  "NYNH&H3265": "344", 
  "NYNH&H6800": "282", 
  "NYNH&H7323": "37", 
  "NYNH&H7372": "217", 
  "NYNH&H8850": "243", 
  "NYNH&H9219": "218", 
  "NYNH&H9560": "33", 
  "P&R0058": "455", 
  "P&R0358": "81", 
  "P&R0612": "325", 
  "P&R0909": "130", 
  "P&R1150": "38", 
  "P&R1583": "22", 
  "P&R1885": "134", 
  "P&R2711": "430", 
  "P&R2990": "181", 
  "P&R3315": "133", 
  "P&R3396": "385", 
  "P&R3482": "144", 
  "P&R4337": "158", 
  "P&R4822": "238", 
  "P&R5399": "31", 
  "P&R5407": "458", 
  "P&R5465": "154", 
  "P&R5635": "310", 
  "P&R6567": "332", 
  "P&R7131": "149", 
  "P&R7282": "146", 
  "P&R7320": "451", 
  "P&R7428": "441", 
  "P&R7512": "151", 
  "P&R7569": "311", 
  "P&R7573": "449", 
  "P&R7683": "404", 
  "P&R8834": "173", 
  "P&R8853": "444", 
  "P&R9143": "432", 
  "PGCC0036": "163", 
  "PGCC0574": "416", 
  "PGCC1876": "334", 
  "PGCC2510": "446", 
  "PGCC2584": "187", 
  "PGCC2600": "330", 
  "PGCC3769": "440", 
  "PGCC4640": "461", 
  "PGCC5225": "169", 
  "PGCC5396": "141", 
  "PGCC5660": "460", 
  "PGCC6493": "179", 
  "PGCC6524": "157", 
  "PGCC6538": "487", 
  "PGCC8228": "159", 
  "PGCC8384": "170", 
  "PGCC8513": "160", 
  "PGCC9000": "162", 
  "PL0279": "468", 
  "PL0701": "392", 
  "PL1273": "473", 
  "PL2192": "343", 
  "PL2322": "224", 
  "PL2589": "220", 
  "PL2789": "213", 
  "PL5213": "234", 
  "PL5465": "24", 
  "PL5694": "386", 
  "PL5734": "46", 
  "PL5846": "237", 
  "PL6905": "40", 
  "PL7466": "335", 
  "PL8472": "475", 
  "PL8820": "428", 
  "PL8892": "419", 
  "PL9034": "453", 
  "PL9079": "228", 
  "PRR0014": "54", 
  "PRR0038": "434", 
  "PRR016": "260", 
  "PRR0215": "340", 
  "PRR028": "67", 
  "PRR0282": "194", 
  "PRR046": "211", 
  "PRR0497": "300", 
  "PRR0537": "156", 
  "PRR0553": "206", 
  "PRR0578": "207", 
  "PRR058": "252", 
  "PRR063": "494", 
  "PRR0784": "164", 
  "PRR0906": "184", 
  "PRR1040": "265", 
  "PRR1060": "209", 
  "PRR1151": "4", 
  "PRR119": "256", 
  "PRR1271": "202", 
  "PRR1287": "406", 
  "PRR1306": "5", 
  "PRR1367": "205", 
  "PRR1398": "296", 
  "PRR1419": "359", 
  "PRR1649": "302", 
  "PRR1792": "360", 
  "PRR184": "275", 
  "PRR1845": "214", 
  "PRR1902": "470", 
  "PRR1950": "304", 
  "PRR1952": "291", 
  "PRR1954": "431", 
  "PRR2006": "59", 
  "PRR2027": "74", 
  "PRR2057": "492", 
  "PRR221": "70", 
  "PRR2280": "466", 
  "PRR234": "53", 
  "PRR2487": "64", 
  "PRR2512": "389", 
  "PRR2627": "288", 
  "PRR2645": "199", 
  "PRR2655": "195", 
  "PRR2746": "452", 
  "PRR2848": "197", 
  "PRR292": "381", 
  "PRR2961": "299", 
  "PRR2973": "437", 
  "PRR2981": "42", 
  "PRR3010": "210", 
  "PRR3065": "63", 
  "PRR333": "380", 
  "PRR336": "191", 
  "PRR3410": "165", 
  "PRR3447": "295", 
  "PRR348": "273", 
  "PRR3717": "329", 
  "PRR376": "382", 
  "PRR3792": "136", 
  "PRR3968": "423", 
  "PRR3986": "175", 
  "PRR4069": "229", 
  "PRR409": "274", 
  "PRR4198": "278", 
  "PRR423": "246", 
  "PRR4281": "333", 
  "PRR4287": "463", 
  "PRR4312": "270", 
  "PRR4479": "75", 
  "PRR450": "1", 
  "PRR451": "21", 
  "PRR475": "254", 
  "PRR4753": "438", 
  "PRR4774": "445", 
  "PRR4778": "193", 
  "PRR478": "248", 
  "PRR4910": "241", 
  "PRR4966": "62", 
  "PRR5055": "200", 
  "PRR525": "379", 
  "PRR5251": "225", 
  "PRR5348": "439", 
  "PRR5384": "57", 
  "PRR5412": "203", 
  "PRR550": "68", 
  "PRR5545": "161", 
  "PRR5547": "284", 
  "PRR5589": "73", 
  "PRR5697": "55", 
  "PRR5819": "309", 
  "PRR5858": "297", 
  "PRR587": "124", 
  "PRR5879": "26", 
  "PRR5893": "32", 
  "PRR5907": "489", 
  "PRR5979": "76", 
  "PRR6030": "303", 
  "PRR6099": "36", 
  "PRR613": "66", 
  "PRR6169": "336", 
  "PRR621": "25", 
  "PRR6224": "436", 
  "PRR6232": "298", 
  "PRR6443": "39", 
  "PRR6444": "204", 
  "PRR6722": "139", 
  "PRR679": "245", 
  "PRR684": "82", 
  "PRR6847": "287", 
  "PRR6862": "65", 
  "PRR6888": "171", 
  "PRR710": "69", 
  "PRR714": "19", 
  "PRR7145": "358", 
  "PRR7207": "143", 
  "PRR7225": "236", 
  "PRR738": "20", 
  "PRR7440": "27", 
  "PRR7480": "49", 
  "PRR760": "250", 
  "PRR7631": "201", 
  "PRR7651": "301", 
  "PRR772": "258", 
  "PRR773": "272", 
  "PRR7859": "198", 
  "PRR7882": "56", 
  "PRR804": "72", 
  "PRR8061": "408", 
  "PRR8093": "148", 
  "PRR8176": "135", 
  "PRR8182": "3", 
  "PRR825": "126", 
  "PRR826": "262", 
  "PRR8281": "208", 
  "PRR833": "544", 
  "PRR8334": "58", 
  "PRR837": "189", 
  "PRR845": "293", 
  "PRR860": "52", 
  "PRR8820": "397", 
  "PRR8841": "6", 
  "PRR886": "71", 
  "PRR8932": "131", 
  "PRR894": "84", 
  "PRR897": "51", 
  "PRR9009": "61", 
  "PRR9031": "292", 
  "PRR9123": "305", 
  "PRR9187": "290", 
  "PRR9517": "464", 
  "PRR9520": "356", 
  "PRR9530": "490", 
  "PRR9609": "174", 
  "PRR976": "378", 
  "PRR9766": "138", 
  "PRR9784": "196", 
  "PRR9825": "289", 
  "PRRMoW554": "77", 
  "SP3626": "338", 
  "SP3699": "277", 
  "SP4301": "402", 
  "SP6046": "407", 
  "SP6068": "413", 
  "SP7538": "34", 
  "SP7843": "264", 
  "SP8351": "454", 
  "TCX1521": "342", 
  "TCX6153": "227", 
  "TCX6846": "230", 
  "TCX7209": "231", 
  "TCX7397": "28", 
  "TELX0150": "223", 
  "TELX3598": "47", 
  "TELX7819": "48", 
  "TELX8214": "387", 
  "TELX8298": "418", 
  "UTLX1387": "29", 
  "UTLX2914": "388", 
  "UTLX6346": "443", 
  "UTLX7756": "493", 
  "UTLX8861": "400", 
  "WCC0822": "142", 
  "WCC0883": "153", 
  "WCC1772": "267", 
  "WCC2355": "349", 
  "WCC2362": "147", 
  "WCC3160": "456", 
  "WCC3311": "168", 
  "WCC3436": "348", 
  "WCC4875": "433", 
  "WCC5273": "488", 
  "WCC5797": "176", 
  "WCC5942": "415", 
  "WCC6005": "266", 
  "WCC6692": "167", 
  "WCC7091": "80", 
  "WCC8029": "145", 
  "WCC8876": "486", 
  "WCC8986": "140", 
  "WCC9485": "465", 
  "WCC9772": "132", 
  "WJ&S2644": "403", 
  "WJ&S5252": "240", 
  "WJ&S5261": "394", 
  "WJ&S5411": "242", 
  "WJ&S7163": "396", 
  "WJ&S7982": "244", 
  "WJ&S9800": "337"
}